{
  "/cv-push/markdown-page-161": {
    "__comp": "1f391b9e",
    "__context": {
      "plugin": "4f896ff8"
    },
    "content": "393be207"
  },
  "/cv-push/docs-0c1": {
    "__comp": "1be78505",
    "__context": {
      "plugin": "1e20c2c6"
    },
    "versionMetadata": "935f2afb"
  },
  "/cv-push/docs/-6e5": {
    "__comp": "17896441",
    "content": "0e384e19"
  },
  "/cv-push/-e7f": {
    "__comp": "c4f5d8e4",
    "__context": {
      "plugin": "4f896ff8"
    },
    "config": "5e9f5e1a"
  }
}